nanoagents/__init__.py
nanoagents/nanoagent.py
nanoagents-0.1.0.dist-info/LICENSE
nanoagents-0.1.0.dist-info/METADATA
nanoagents-0.1.0.dist-info/WHEEL
nanoagents-0.1.0.dist-info/RECORD
