Metadata-Version: 2.1
Name: nanoagents
Version: 0.1.0
Summary: A nano, minimalistic, and lightweight library for building ReACT-based AI agents that use tools to solve tasks.
Author: tnahddisttud
Author-email: siddhantp73@gmail.com
Requires-Python: >=3.11,<4.0
Classifier: Programming Language :: Python :: 3
Classifier: Programming Language :: Python :: 3.11
Classifier: Programming Language :: Python :: 3.12
